dheapy/__init__.py
dheapy/dheapy.py
dheapy-0.1.5.dist-info/LICENSE.txt
dheapy-0.1.5.dist-info/METADATA
dheapy-0.1.5.dist-info/WHEEL
dheapy-0.1.5.dist-info/top_level.txt
dheapy-0.1.5.dist-info/RECORD
