Metadata-Version: 2.1
Name: dheapy
Version: 0.1.5
Summary: Max/min d-ary heap implementation for priority queues.
Author-email: "Vivi Andasari, PhD" <vandasari@gmail.com>
Project-URL: Homepage, https://github.com/vandasari/dheapy
Project-URL: Repository, https://github.com/vandasari/dheapy
Project-URL: Issues, https://github.com/vandasari/dheapy/issues
Keywords: priority queue,heap,max-heap,min-heap,d-ary heap,binary heap,ternary heap,quaternary heap,quinary heap
Classifier: Programming Language :: Python :: 3
Classifier: License :: OSI Approved :: MIT License
Classifier: Operating System :: OS Independent
Requires-Python: >=3.9
License-File: LICENSE.txt
